{
    "id": 32,
    "location": "{\"type\":\"Point\",\"coordinates\":[-1.555811583,53.80672801]}",
    "work": [
        "close",
        "friends",
        "group"
    ],
    "atmosphere": [
        "relaxed",
        "modern",
        "social",
        "friendly"
    ],
    "images": [],
    "facilities": [
        "food_drink",
        "daylight",
        "free_wifi",
        "laptops_allowed",
        "sockets",
        "signal",
        "toilets",
        "refreshments",
        "break"
    ],
    "title": "General Seating Areas - Leeds University Union - Foyer",
    "basic_info": "Ground Floor, Leeds University Union. Campus Map Ref 32",
    "description": "Busy study place for people that like working alonside others . Couches with big tables can be used for comfortable group working on a nice environment .Extra couches on the side for anybody that wants to read or take a break .",
    "access": "Anyone (public)",
    "space_type": "General Seating Area",
    "library": false,
    "address": "University of Leeds Campus, Woodhouse Lane, Leeds LS2 9JT",
    "building": "Leeds University Union",
    "floor": "Ground floor",
    "restricted": false,
    "restriction": "",
    "disabled_access": true,
    "url": "https://www.luu.org.uk/",
    "phone_number": "0113 3801 400",
    "twitter_screen_name": "LeedsUniUnion",
    "facebook_url": "https://www.facebook.com/leedsuniversityunion/",
    "campusmap_url": "https://www.leeds.ac.uk/campusmap?location=17489",
    "noise": "Animated discussion",
    "tags": [],
    "opening_hours": {
        "monday": {
            "open": true,
            "from": "8:30",
            "to": "22:00"
        },
        "tuesday": {
            "open": true,
            "from": "8:30",
            "to": "22:00"
        },
        "wednesday": {
            "open": true,
            "from": "8:30",
            "to": "22:00"
        },
        "thursday": {
            "open": true,
            "from": "8:30",
            "to": "22:00"
        },
        "friday": {
            "open": true,
            "from": "8:30",
            "to": "22:00"
        },
        "saturday": {
            "open": false,
            "from": "",
            "to": ""
        },
        "sunday": {
            "open": false,
            "from": "",
            "to": ""
        }
    }
}