{
    "facilities": [
        "daylight",
        "large_desks",
        "free_wifi",
        "computers",
        "laptops_allowed",
        "sockets",
        "signal",
        "whiteboards",
        "projector",
        "toilets",
        "bike_racks",
        "gender_neutral_toilets",
        "wheelchair_accessible",
        "blue_badge_parking"
    ],
    "atmosphere": [
        "disciplined",
        "modern"
    ],
    "access": "University Staff and Students",
    "disabled_access": true,
    "opening_hours": {
        "monday": {
            "open": true,
            "from": "9:00",
            "to": "18:00"
        },
        "tuesday": {
            "open": true,
            "from": "9:00",
            "to": "18:00"
        },
        "wednesday": {
            "open": true,
            "from": "9:00",
            "to": "18:00"
        },
        "thursday": {
            "open": true,
            "from": "9:00",
            "to": "18:00"
        },
        "friday": {
            "open": true,
            "from": "9:00",
            "to": "17:00"
        },
        "saturday": {
            "open": false,
            "from": "",
            "to": ""
        },
        "sunday": {
            "open": false,
            "from": "",
            "to": ""
        }
    },
    "slug": "e-c-stoner-building-668",
    "floor": "Level 6",
    "restriction": "",
    "campusmap_url": "https://www.leeds.ac.uk/campusmap?location=17406",
    "published": false,
    "imagealt": "E C Stoner Building - 6.68",
    "url": "https://mytimetable.leeds.ac.uk/link?timetable.id=202223!location!6856E1BEE4EE6ABF22261FF5840C4D78",
    "campusmap_ref": "73",
    "work": [
        "private",
        "close"
    ],
    "twitter_screen_name": "",
    "space_type": "IT Cluster",
    "building": "E C Stoner Building",
    "address": "University of Leeds, LS2 9JT",
    "location": "{\"type\":\"Point\",\"coordinates\":[-1.5521271182627379,53.80538144]}",
    "facebook_url": "",
    "title": "E C Stoner Building - 6.68",
    "tags": [],
    "noise": "Strictly silent",
    "phone_number": "",
    "restricted": true,
    "id": 52,
    "image": "",
    "description": "Large cluster with multiple computers and comfortable chairs. 47 seat capacity",
    "url_text": "View timetable for E C Stoner Building - 6.68",
    "phone_text": ""
}